bodosdk/__init__.py
bodosdk/_version.py
bodosdk/base.py
bodosdk/deprecation_decorator.py
bodosdk/exceptions.py
bodosdk/interfaces.py
bodosdk/api/__init__.py
bodosdk/api/auth.py
bodosdk/api/base.py
bodosdk/api/billing.py
bodosdk/api/catalog.py
bodosdk/api/cloud_config.py
bodosdk/api/cluster.py
bodosdk/api/cron_job.py
bodosdk/api/helpers.py
bodosdk/api/instance_role.py
bodosdk/api/job.py
bodosdk/api/job_tpl.py
bodosdk/api/request_wrapper.py
bodosdk/api/sdk.py
bodosdk/api/secret_group.py
bodosdk/api/secrets.py
bodosdk/api/workspace.py
bodosdk/api/models/__init__.py
bodosdk/api/models/base.py
bodosdk/api/models/catalog.py
bodosdk/api/models/cloud_config.py
bodosdk/api/models/cluster.py
bodosdk/api/models/cron_job.py
bodosdk/api/models/instance_role.py
bodosdk/api/models/job.py
bodosdk/api/models/secret_group.py
bodosdk/api/models/secrets.py
bodosdk/api/models/workspace.py
bodosdk/clients/__init__.py
bodosdk/clients/catalog.py
bodosdk/clients/cluster.py
bodosdk/clients/cron_job.py
bodosdk/clients/instance_role.py
bodosdk/clients/job.py
bodosdk/clients/job_tpl.py
bodosdk/clients/organization.py
bodosdk/clients/secret.py
bodosdk/clients/workspace.py
bodosdk/db/__init__.py
bodosdk/db/args_parser.py
bodosdk/db/connection.py
bodosdk/db/downloader.py
bodosdk/db/exc.py
bodosdk/models/__init__.py
bodosdk/models/catalog.py
bodosdk/models/cloud_config.py
bodosdk/models/cluster.py
bodosdk/models/common.py
bodosdk/models/cron_job.py
bodosdk/models/instance_role.py
bodosdk/models/job.py
bodosdk/models/secret.py
bodosdk/models/workspace.py
bodosdk-2.3.2.dist-info/licenses/LICENSE
bodosdk-2.3.2.dist-info/METADATA
bodosdk-2.3.2.dist-info/WHEEL
bodosdk-2.3.2.dist-info/top_level.txt
bodosdk-2.3.2.dist-info/RECORD
