Metadata-Version: 2.4
Name: bodosdk
Version: 2.3.2
Summary: Bodo Platform SDK 2.3.2
Home-page: https://github.com/bodo-ai/bodo-sdk
Author: Bodo, Inc.
Author-email: noreply@bodo.ai
Classifier: Programming Language :: Python :: 3
Classifier: Programming Language :: Python :: 3.8
Classifier: Programming Language :: Python :: 3.9
Classifier: Programming Language :: Python :: 3.10
Classifier: Programming Language :: Python :: 3.11
Classifier: Programming Language :: Python :: 3.12
Classifier: License :: OSI Approved :: MIT License
Classifier: Operating System :: OS Independent
Requires-Python: >=3.8
License-File: LICENSE
Requires-Dist: pydantic~=1.9
Requires-Dist: requests~=2.28
Requires-Dist: pyjwt~=2.9.0
Requires-Dist: typing_extensions>=4
Requires-Dist: callee~=0.3.1
Requires-Dist: pandas
Requires-Dist: pyarrow
Dynamic: author
Dynamic: author-email
Dynamic: classifier
Dynamic: description
Dynamic: description-content-type
Dynamic: home-page
Dynamic: license-file
Dynamic: requires-dist
Dynamic: requires-python
Dynamic: summary
